easylog/__init__.py
easylog/easylog.py
mepybase/__init__.py
mepybase/easylog/__init__.py
mepybase/easylog/easylog.py
mepybase-1.0.dist-info/METADATA
mepybase-1.0.dist-info/WHEEL
mepybase-1.0.dist-info/top_level.txt
mepybase-1.0.dist-info/RECORD
