Metadata-Version: 2.4
Name: mepybase
Version: 1.0
Summary: Mellon self py base utils
Home-page: https://github.com/mellon/mepybase/
Author: mellon
Author-email: mellon.email@example.com
Classifier: Programming Language :: Python :: 3
Classifier: License :: OSI Approved :: MIT License
Classifier: Operating System :: OS Independent
Requires-Python: >=3.6
Requires-Dist: colorama
Dynamic: author
Dynamic: author-email
Dynamic: classifier
Dynamic: description
Dynamic: description-content-type
Dynamic: home-page
Dynamic: requires-dist
Dynamic: requires-python
Dynamic: summary
